aiotorrent/__init__.py
aiotorrent/aiotorrent.py
aiotorrent/core/file_utils.py
aiotorrent/core/message_generator.py
aiotorrent/core/response_handler.py
aiotorrent/core/response_parser.py
aiotorrent/core/trackers.py
aiotorrent/core/util.py
aiotorrent/downloader.py
aiotorrent/peer.py
aiotorrent/piece.py
aiotorrent/tracker_factory.py
python_aiotorrent-0.8.3.dist-info/LICENSE
python_aiotorrent-0.8.3.dist-info/METADATA
python_aiotorrent-0.8.3.dist-info/WHEEL
python_aiotorrent-0.8.3.dist-info/RECORD
