Metadata-Version: 2.1
Name: python-aiotorrent
Version: 0.8.3
Summary: An ultra-lightweight torrent library written in pure Python.
Home-page: https://github.com/Mys7erio/aiotorrent
Keywords: python,python3,bittorrent,bittorrent-client,downloading,streaming
Author: Shakir
Author-email: shakirali.sacube@gmail.com
Requires-Python: >=3.11,<4.0
Classifier: Development Status :: 4 - Beta
Classifier: Environment :: Web Environment
Classifier: Intended Audience :: Developers
Classifier: Operating System :: OS Independent
Classifier: Programming Language :: Python
Classifier: Programming Language :: Python :: 3
Classifier: Programming Language :: Python :: 3.11
Classifier: Programming Language :: Python :: 3.12
Classifier: Topic :: Communications :: File Sharing
Classifier: Topic :: Internet :: WWW/HTTP :: HTTP Servers
Classifier: Topic :: Multimedia
Classifier: Topic :: Software Development :: Libraries :: Python Modules
Provides-Extra: stream-support
Requires-Dist: bitstring (>=4.0.1,<5.0.0)
Requires-Dist: fast-bencode (>=1.1.4,<2.0.0)
Requires-Dist: starlette (>=0.32.0.post1,<0.33.0) ; extra == "stream-support"
Requires-Dist: uvicorn (>=0.24.0.post1,<0.25.0) ; extra == "stream-support"
Project-URL: Repository, https://github.com/Mys7erio/aiotorrent
